fxq/commons/__init__.py
fxq/commons/_reflection_utils.py
fxq/commons/_requests_adapter.py
fxq/commons/json_requests.py
fxq/commons/marshalling.py
fxq/core/__init__.py
fxq/core/beans/__init__.py
fxq/core/beans/factory/BeanFactory.py
fxq/core/beans/factory/__init__.py
fxq/core/beans/factory/annotation/Autowired.py
fxq/core/beans/factory/annotation/__init__.py
fxq/core/context/ApplicationContext.py
fxq/core/context/__init__.py
fxq/core/stereotype/Component.py
fxq/core/stereotype/__init__.py
fxq/env/__init__.py
fxq/model/__init__.py
fxq/model/country.py
fxq/model/currency.py
fxq/model/event.py
fxq_commons-1.1.1.dist-info/LICENSE.md
fxq_commons-1.1.1.dist-info/METADATA
fxq_commons-1.1.1.dist-info/WHEEL
fxq_commons-1.1.1.dist-info/top_level.txt
fxq_commons-1.1.1.dist-info/RECORD
