Metadata-Version: 2.1
Name: fxq-commons
Version: 1.1.1
Summary: Common python utilities and scripts for fxq labs
Home-page: https://bitbucket.org/fxqlabs-oss/fxq-commons/
Author: Jonathan Turnock
Author-email: jonathan.turnock@outlook.com
License: MIT
Platform: UNKNOWN
Requires-Dist: PyYAML
Requires-Dist: stringcase
Requires-Dist: requests
Requires-Dist: multidispatch
Requires-Dist: jsonpickle
